md2wxhtml/__init__.py
md2wxhtml/main.py
md2wxhtml/core/__init__.py
md2wxhtml/core/converter.py
md2wxhtml/core/markdown_parser.py
md2wxhtml/core/merger.py
md2wxhtml/models/__init__.py
md2wxhtml/models/code_block.py
md2wxhtml/models/processing_result.py
md2wxhtml/processors/__init__.py
md2wxhtml/processors/code_processor.py
md2wxhtml/processors/content_processor.py
md2wxhtml/processors/themes/__init__.py
md2wxhtml/processors/themes/blue.py
md2wxhtml/processors/themes/dark.py
md2wxhtml/processors/themes/default.py
md2wxhtml/processors/themes/github.py
md2wxhtml/processors/themes/green.py
md2wxhtml/processors/themes/hammer.py
md2wxhtml/processors/themes/red.py
md2wxhtml/utils/__init__.py
md2wxhtml/utils/placeholder_manager.py
md2wxhtml-0.1.13.dist-info/licenses/LICENSE
md2wxhtml-0.1.13.dist-info/METADATA
md2wxhtml-0.1.13.dist-info/WHEEL
md2wxhtml-0.1.13.dist-info/entry_points.txt
md2wxhtml-0.1.13.dist-info/top_level.txt
md2wxhtml-0.1.13.dist-info/RECORD
