Metadata-Version: 2.4
Name: md2wxhtml
Version: 0.1.13
Summary: Add your description here
Requires-Python: >=3.12.10
License-File: LICENSE
Requires-Dist: pygments
Requires-Dist: markdown
Requires-Dist: premailer
Requires-Dist: beautifulsoup4
Dynamic: license-file
